yklibpy/__init__.py
yklibpy/common/__init__.py
yklibpy/common/convert_yaml_strip_tags.py
yklibpy/common/env.py
yklibpy/common/info.py
yklibpy/common/util.py
yklibpy/common/util_yaml.py
yklibpy/db/__init__.py
yklibpy/db/db_base.py
yklibpy/db/db_yaml.py
yklibpy/htmlparser/__init__.py
yklibpy/htmlparser/amazon.py
yklibpy/htmlparser/amazonsavedcartscraper.py
yklibpy/htmlparser/app.py
yklibpy/htmlparser/ascraper.py
yklibpy/htmlparser/configprepare.py
yklibpy/htmlparser/fanzadoujinpurchasedscraper.py
yklibpy/htmlparser/fanzadoujinscraper.py
yklibpy/htmlparser/h3scraper.py
yklibpy/htmlparser/htmlop.py
yklibpy/htmlparser/kuscraper.py
yklibpy/htmlparser/preparex.py
yklibpy/htmlparser/progress.py
yklibpy/htmlparser/py.typed
yklibpy/htmlparser/scraper.py
yklibpy/htmlparser/udemyscraper.py
yklibpy/htmlparser/misc/__init__.py
yklibpy/htmlparser/misc/anchortaginfo.py
yklibpy/htmlparser/misc/anchortagx.py
yklibpy/htmlparser/misc/priceinfo.py
yklibpy/htmlparser/misc/tagx.py
yklibpy/tomlop/__init__.py
yklibpy/tomlop/tomlop.py
yklibpy-0.1.11.dist-info/METADATA
yklibpy-0.1.11.dist-info/WHEEL
yklibpy-0.1.11.dist-info/entry_points.txt
yklibpy-0.1.11.dist-info/RECORD
