Metadata-Version: 2.4
Name: yklibpy
Version: 0.1.11
Summary: Utilty Library by ykominami
Project-URL: Homepage, https://github.com/ykominami/yklibpy
Project-URL: Repository, https://github.com/ykominami/yklibpy
Author: Yasuo Kominami
License-Expression: MIT
Classifier: Development Status :: 3 - Alpha
Classifier: Intended Audience :: Developers
Classifier: License :: OSI Approved :: MIT License
Classifier: Programming Language :: Python :: 3
Classifier: Programming Language :: Python :: 3.10
Classifier: Programming Language :: Python :: Implementation :: PyPy
Requires-Python: >=3.14
Requires-Dist: bs4>=0.0.2
Requires-Dist: chardet>=5.2.0
Requires-Dist: html5lib>=1.1
Requires-Dist: pyyaml>=6.0.3
Requires-Dist: toml>=0.10.2
